{
  "Experiments": {
    "DMC_EMC_DEC": {
      "Set1": {
        "p": [
          101.29,
          101.3,
          101.29,
          101.29,
          101.3,
          101.29,
          101.29,
          101.29
        ],
        "T": [
          373.22,
          376.3,
          380.84,
          383.4,
          386.07,
          388.18,
          389.75,
          391.25
        ],
        "x1": [
          0.373,
          0.305,
          0.232,
          0.184,
          0.146,
          0.13,
          0.098,
          0.092
        ],
        "x2": [
          0.616,
          0.547,
          0.406,
          0.353,
          0.271,
          0.216,
          0.185,
          0.148
        ],
        "x3": [
          0.012,
          0.148,
          0.361,
          0.463,
          0.583,
          0.654,
          0.717,
          0.759
        ],
        "y1": [
          0.514,
          0.463,
          0.41,
          0.356,
          0.316,
          0.268,
          0.237,
          0.21
        ],
        "y2": [
          0.476,
          0.465,
          0.397,
          0.373,
          0.313,
          0.276,
          0.238,
          0.21
        ],
        "y3": [
          0.01,
          0.072,
          0.193,
          0.271,
          0.371,
          0.456,
          0.525,
          0.58
        ]
      }
    },
    "DMC_DEC_PC": {
      "Set1": {
        "p": [
          101.03,
          101.24,
          101.19,
          101.05,
          101.18
        ],
        "T": [
          375.87,
          384.62,
          407.17,
          412.77,
          438.59
        ],
        "x1": [
          0.504,
          0.333,
          0.163,
          0.135,
          0.07
        ],
        "x2": [
          0.387,
          0.31,
          0.18,
          0.138,
          0.081
        ],
        "x3": [
          0.109,
          0.357,
          0.657,
          0.727,
          0.849
        ],
        "y1": [
          0.795,
          0.733,
          0.648,
          0.652,
          0.553
        ],
        "y2": [
          0.202,
          0.26,
          0.327,
          0.314,
          0.353
        ],
        "y3": [
          0.003,
          0.007,
          0.025,
          0.034,
          0.094
        ]
      },
      "Set2": {
        "p": [
          24.93,
          24.9,
          24.91,
          24.93,
          24.94,
          24.87
        ],
        "T": [
          336.36,
          342.2,
          349.77,
          361.74,
          372.04,
          418.5
        ],
        "x1": [
          0.518,
          0.367,
          0.247,
          0.145,
          0.096,
          0.026
        ],
        "x2": [
          0.378,
          0.305,
          0.218,
          0.145,
          0.1,
          0.031
        ],
        "x3": [
          0.103,
          0.328,
          0.535,
          0.71,
          0.804,
          0.942
        ],
        "y1": [
          0.831,
          0.787,
          0.758,
          0.699,
          0.676,
          0.463
        ],
        "y2": [
          0.168,
          0.209,
          0.236,
          0.287,
          0.301,
          0.313
        ],
        "y3": [
          0.001,
          0.004,
          0.007,
          0.014,
          0.023,
          0.224
        ]
      }
    },
    "EMC_PC_EC": {
      "Set1": {
        "p": [
          101.18,
          101.25,
          101.22,
          101.13,
          101.23,
          101.28
        ],
        "T": [
          401.64,
          409.02,
          426.66,
          407.65,
          423.47,
          435.92
        ],
        "x1": [
          0.348,
          0.275,
          0.175,
          0.312,
          0.198,
          0.149
        ],
        "x2": [
          0.057,
          0.191,
          0.42,
          0.433,
          0.613,
          0.649
        ],
        "x3": [
          0.595,
          0.535,
          0.406,
          0.255,
          0.189,
          0.202
        ],
        "y1": [
          0.981,
          0.973,
          0.945,
          0.974,
          0.948,
          0.912
        ],
        "y2": [
          0.009,
          0.014,
          0.036,
          0.019,
          0.042,
          0.07
        ],
        "y3": [
          0.01,
          0.012,
          0.019,
          0.007,
          0.01,
          0.017
        ]
      },
      "Set2": {
        "p": [
          24.97,
          24.98,
          24.91,
          24.93,
          24.93,
          24.96,
          24.99,
          24.98,
          24.94,
          24.96
        ],
        "T": [
          354.65,
          360.7,
          368.54,
          376.04,
          385.77,
          396.28,
          418.25,
          357.54,
          366.27,
          374.03
        ],
        "x1": [
          0.386,
          0.279,
          0.211,
          0.161,
          0.115,
          0.085,
          0.041,
          0.346,
          0.242,
          0.194
        ],
        "x2": [
          0.07,
          0.192,
          0.397,
          0.524,
          0.641,
          0.709,
          0.804,
          0.421,
          0.578,
          0.615
        ],
        "x3": [
          0.544,
          0.529,
          0.391,
          0.315,
          0.245,
          0.206,
          0.155,
          0.233,
          0.18,
          0.19
        ],
        "y1": [
          0.988,
          0.986,
          0.979,
          0.966,
          0.952,
          0.93,
          0.805,
          0.978,
          0.979,
          0.964
        ],
        "y2": [
          0.008,
          0.009,
          0.015,
          0.025,
          0.039,
          0.059,
          0.172,
          0.019,
          0.017,
          0.027
        ],
        "y3": [
          0.004,
          0.005,
          0.006,
          0.008,
          0.009,
          0.011,
          0.022,
          0.004,
          0.004,
          0.009
        ]
      }
    }
  },
  "Literature": {}
}